{
    "context": {
        "params": {
            "legend": "Was this page useful?",
            "groupId": "feedback",
            "radios": [
                {
                    "id": "feedback-yes",
                    "label": "Yes",
                    "value": "yes"
                },
                {
                    "id": "feedback-no",
                    "label": "No",
                    "value": "no"
                },
                {
                    "id": "feedback-maybe",
                    "label": "Maybe",
                    "value": "maybe"
                }
            ]
        }
    },
    "variants": [
        {
            "name": "Hint text",
            "context": {
                "params": {
                    "hint": "Select an option"
                }
            }
        },
        {
            "name": "Hint text per checkbox",
            "context": {
                "params": {
                    "legend": "How will the payments be paid in?",
                    "hint": "Select an option",
                    "groupId": "payments",
                    "radios": [
                        {
                            "id": "advance",
                            "label": "Advance",
                            "hint": "This means you're paid for the period coming up, for example the month ahead"
                        },
                        {
                            "id": "arrears",
                            "label": "Arrears",
                            "hint": "This means you're paid for the time that's just passed, for example for the last month"
                        }
                    ]
                }
            }
        },
        {
            "name": "Small checkboxes",
            "context": {
                "params": {
                    "hint": "Select an option",
                    "radios": [
                        {
                            "id": "feedback-yes",
                            "label": "Yes",
                            "value": "yes",
                            "small": true
                        },
                        {
                            "id": "feedback-no",
                            "label": "No",
                            "value": "no",
                            "small": true
                        },
                        {
                            "id": "feedback-maybe",
                            "label": "Maybe",
                            "value": "maybe",
                            "small": true
                        }
                    ]
                }
            }
        },
        {
            "name": "Inline radios",
            "context": {
                "params": {
                    "legend": "Is a letting agency managing the property?",
                    "inline": true,
                    "radios": [
                        {
                            "id": "feedback-yes",
                            "label": "Yes",
                            "value": "yes"
                        },
                        {
                            "id": "feedback-no",
                            "label": "No",
                            "value": "no"
                        }
                    ]
                }
            }
        },
        {
            "name": "Error state",
            "context": {
                "params": {
                    "hint": "Select an option",
                    "error": "This field is required"
                }
            }
        },
        {
            "name": "Inline error state",
            "context": {
                "params": {
                    "legend": "Is a letting agency managing the property?",
                    "error": "This field is required",
                    "inline": true,
                    "radios": [
                        {
                            "id": "feedback-yes",
                            "label": "Yes",
                            "value": "yes"
                        },
                        {
                            "id": "feedback-no",
                            "label": "No",
                            "value": "no"
                        }
                    ]
                }
            }
        }
    ]
}
