{
    "label": "Search result",
    "context": {
        "params": {
            "element": "div",
            "heading": "Crofting community right to buy",
            "headingLevel": "h3",
            "content": "Information and guidance regarding the crofting community right to buy.",
            "link": "#"
        }
    },
    "variants": [
        {
            "name": "No content",
            "label": "No content",
            "context": {
                "params": {
                    "heading": "Crofting community right to buy",
                    "link": "#",
                    "content": false
                }
            }
        },
        {
            "name": "Character limits",
            "label": "Character limits",
            "context": {
                "params": {
                    "heading": "Proposals on secondary legislation the Land Reform (Scotland) Act 2003 part three: crofting community right to buy as amended by the Community Empowerment (Scotland) Act 2015: consultation",
                    "headingLevel": "h3",
                    "link": "#",
                    "content": "Consultation relating to secondary legislation for the Land Reform (Scotland) Act 2003 part three, crofting community right to buy as amended by the Community ..." 
                }
            }
        },
        {
            "name": "Metadata",
            "label": "Metadata",
            "context": {
                "params": {
                    "metadata": {
                        "params": {
                            "modifiers": "ds_search-result__metadata  ds_metadata--inline",
                            "items": [
                                {
                                    "key": "Format",
                                    "value": "Policy",
                                    "hideKey": true
                                }
                            ]
                        }
                    },
                    "heading": "Crofting community right to buy",
                    "link": "#",
                    "content": false
                }
            }
        },
        {
            "name": "Metadata and content",
            "label": "Metadata and content",
            "context": {
                "params": {
                    "metadata": {
                        "params": {
                            "modifiers": "ds_search-result__metadata  ds_metadata--inline",
                            "items": [
                                {
                                    "key": "Format",
                                    "value": "Publication - Consultation paper",
                                    "hideKey": true
                                },
                                {
                                    "key": "Date",
                                    "value": "13 August 2021",
                                    "hideKey": true
                                }
                            ]
                        }
                    },
                    "heading": "Crofting community right to buy",
                    "link": "#",
                    "content": "Information and guidance regarding the crofting community right to buy."
                }
            }
        },
        {
            "name": "Highlighted search match",
            "label": "Highlighted search match",
            "context": {
                "params": {
                    "metadata": {
                        "params": {
                            "modifiers": "ds_search-result__metadata  ds_metadata--inline",
                            "items": [
                                {
                                    "key": "Format",
                                    "value": "Publication - Consultation paper",
                                    "hideKey": true
                                },
                                {
                                    "key": "Date",
                                    "value": "13 August 2021",
                                    "hideKey": true
                                }
                            ]
                        }
                    },
                    "heading": "Crofting community right to buy",
                    "link": "#",
                    "content": "Information and guidance regarding the <mark>crofting</mark> community right to buy."
                }
            }
        },
        {
            "name": "Parent link",
            "label": "Parent link",
            "context": {
                "params": {
                    "metadata": {
                        "params": {
                            "modifiers": "ds_search-result__metadata  ds_metadata--inline",
                            "items": [
                                {
                                    "key": "Format",
                                    "value": "Publication - Consultation paper",
                                    "hideKey": true
                                },
                                {
                                    "key": "Date",
                                    "value": "13 August 2021",
                                    "hideKey": true
                                }
                            ]
                        }
                    },
                    "heading": "Crofting community right to buy",
                    "link": "#",
                    "content": "Information and guidance regarding the crofting community right to buy.",
                    "parent": {
                        "heading": "Part of:",
                        "links": [
                            {
                                "linkLabel": "Land reform",
                                "link": "#"
                            }
                        ]
                    }
                }
            }
        },
        {
            "name": "Multiple parent links",
            "label": "Multiple parent links",
            "context": {
                "params": {
                    "metadata": {
                        "params": {
                            "modifiers": "ds_search-result__metadata  ds_metadata--inline",
                            "items": [
                                {
                                    "key": "Format",
                                    "value": "Publication - Consultation paper",
                                    "hideKey": true
                                },
                                {
                                    "key": "Date",
                                    "value": "13 August 2021",
                                    "hideKey": true
                                }
                            ]
                        }
                    },
                    "heading": "Crofting community right to buy",
                    "link": "#",
                    "content": "Information and guidance regarding the crofting community right to buy.",
                    "parent": {
                        "heading": "Part of:",
                        "links": [
                            {
                                "linkLabel": "Land reform",
                                "link": "#"
                            },
                            {
                                "linkLabel": "Rural affairs",
                                "link": "#"
                            }
                        ]
                    }
                }
            }
        },
        {
            "name": "Result with image",
            "label": "Result with image",
            "context": {
                "params": {
                    "heading": "First Minister",
                    "link": "#",
                    "image": "/assets/images/placeholders/thistles.jpg",
                    "subHeading": "Incumbent's name",
                    "subHeadingLevel": "h4",
                    "content": "The First Minister is head of the Scottish Government and has ultimate responsibility for all policy and decisions."
                }
            }
        },
        {
            "name": "Image and metadata",
            "label": "Image and metadata",
            "status": "wip",
            "context": {
                "params": {
                    "metadata": {
                        "params": {
                            "modifiers": "ds_search-result__metadata  ds_metadata--inline",
                            "items": [
                                {
                                    "key": "Date",
                                    "value": "13 August 2021",
                                    "hideKey": true
                                }
                            ]
                        }
                    },
                    "heading": "First Minister",
                    "link": "#",
                    "image": "/assets/images/placeholders/thistles.jpg",
                    "subHeading": "Incumbent's name",
                    "subHeadingLevel": "h4",
                    "content": "The First Minister is head of the Scottish Government and has ultimate responsibility for all policy and decisions."
                }
            }
        },
        {
            "name": "Image with metadata and parent",
            "label": "Image with metadata and parent",
            "status": "wip",
            "context": {
                "params": {
                    "metadata": {
                        "params": {
                            "modifiers": "ds_search-result__metadata  ds_metadata--inline",
                            "items": [
                                {
                                    "key": "Date",
                                    "value": "13 August 2021",
                                    "hideKey": true
                                }
                            ]
                        }
                    },
                    "heading": "First Minister",
                    "link": "#",
                    "image": "/assets/images/placeholders/thistles.jpg",
                    "subHeading": "Incumbent's name",
                    "subHeadingLevel": "h4",
                    "content": "The First Minister is head of the Scottish Government and has ultimate responsibility for all policy and decisions.",
                    "parent": {
                        "heading": "Part of:",
                        "links": [
                            {
                                "linkLabel": "Land reform",
                                "link": "#"
                            }
                        ]
                    }
                }
            }
        },
        {
            "name": "Promoted",
            "label": "Promoted",
            "context": {
                "params": {
                    "metadata": {
                        "params": {
                            "modifiers": "ds_search-result__metadata  ds_metadata--inline",
                            "items": [
                                {
                                    "key": "Format",
                                    "value": "Publication - Consultation paper",
                                    "hideKey": true
                                },
                                {
                                    "key": "Date",
                                    "value": "13 August 2021",
                                    "hideKey": true
                                }
                            ]
                        }
                    },
                    "promoted": "Recommended by gov.scot",
                    "heading": "Crofting community right to buy",
                    "link": "#",
                    "content": "Information and guidance regarding the crofting community right to buy."
                }
            }
        },
        {
            "name": "Promoted with parent",
            "label": "Promoted with parent",
            "status": "prototype",
            "context": {
                "params": {
                    "metadata": {
                        "params": {
                            "modifiers": "ds_search-result__metadata  ds_metadata--inline",
                            "items": [
                                {
                                    "key": "Format",
                                    "value": "Publication - Consultation paper",
                                    "hideKey": true
                                },
                                {
                                    "key": "Date",
                                    "value": "13 August 2021",
                                    "hideKey": true
                                }
                            ]
                        }
                    },
                    "promoted": "Recommended by gov.scot",
                    "heading": "Crofting community right to buy",
                    "link": "#",
                    "content": "Information and guidance regarding the crofting community right to buy.",
                    "parent": {
                        "heading": "Part of:",
                        "links": [
                            {
                                "linkLabel": "Land reform",
                                "link": "#"
                            }
                        ]
                    }
                }
            }
        },
        {
            "name": "Promoted with image",
            "label": "Promoted with image",
            "status": "prototype",
            "context": {
                "params": {
                    "promoted": "Recommended by gov.scot",
                    "heading": "First Minister",
                    "link": "#",
                    "image": "/assets/images/placeholders/thistles.jpg",
                    "subHeading": "Incumbent's name",
                    "subHeadingLevel": "h4",
                    "content": "The First Minister is head of the Scottish Government and has ultimate responsibility for all policy and decisions."
                }
            }
        },
        {
            "name": "Sub links",
            "label": "Sub links",
            "status": "prototype",
            "context": {
                "params": {
                    "heading": "Apply for a new Blue Badge",
                    "link": "#",
                    "content": "If you struggle to get around and use a car you could get a Blue Badge. A Blue Badge lets you park closer to where you're going.",
                    "subLinksHeadingLevel": "h4",
                    "subLinks": [
                        {
                            "linkLabel": "Renew a Blue Badge",
                            "link": "#"
                        },
                        {
                            "linkLabel": "Eligibility",
                            "link": "#"
                        },
                        {
                            "linkLabel": "Using your Blue Badge",
                            "link": "#"
                        },
                        {
                            "linkLabel": "Report a lost, stolen or misused Blue Badge",
                            "link": "#"
                        },
                        {
                            "linkLabel": "Changing or handing back a Blue Badge",
                            "link": "#"
                        },
                        {
                            "linkLabel": "Get further help with a Blue Badge",
                            "link": "#"
                        }
                    ]
                }
            }
        },
        {
            "name": "Everything",
            "label": "Everything",
            "status": "invalid",
            "context": {
                "params": {
                    "metadata": {
                        "params": {
                            "modifiers": "ds_search-result__metadata ds_metadata--inline",
                            "items": [
                                {
                                    "key": "Date",
                                    "value": "13 August 2021",
                                    "hideKey": true
                                }
                            ]
                        }
                    },
                    "heading": "First Minister",
                    "link": "#",
                    "image": "/assets/images/placeholders/thistles.jpg",
                    "subHeading": "Incumbent's name",
                    "subHeadingLevel": "h4",
                    "content": "The First Minister is head of the Scottish Government and has ultimate responsibility for all policy and decisions.",
                    "parent": {
                        "heading": "Part of:",
                        "links": [
                            {
                                "linkLabel": "Land reform",
                                "link": "#"
                            }
                        ]
                    },
                    "subLinksHeadingLevel": "h4",
                    "subLinks": [
                        {
                            "linkLabel": "Renew a Blue Badge",
                            "link": "#"
                        },
                        {
                            "linkLabel": "Eligibility",
                            "link": "#"
                        },
                        {
                            "linkLabel": "Using your Blue Badge",
                            "link": "#"
                        },
                        {
                            "linkLabel": "Report a lost, stolen or misused Blue Badge",
                            "link": "#"
                        },
                        {
                            "linkLabel": "Changing or handing back a Blue Badge",
                            "link": "#"
                        },
                        {
                            "linkLabel": "Get further help with a Blue Badge",
                            "link": "#"
                        }
                    ]
                }
            }
        },
        {
            "name": "Deprecated",
            "label": "Deprecated markup",
            "status": "invalid",
            "context": {
                "params": {
                    "metadata": {
                        "params": {
                            "modifiers": "ds_search-result__metadata ds_metadata--inline",
                            "items": [
                                {
                                    "key": "Type",
                                    "value": "Consultation paper",
                                    "hideKey": true,
                                    "isLabel": true
                                },
                                {
                                    "key": "Publish date",
                                    "value": "13 August 2021",
                                    "hideKey": true
                                }
                            ]
                        }
                    },
                    "heading": "Crofting community right to buy",
                    "link": "#",
                    "content": "Information and guidance regarding the crofting community right to buy."
                }
            }
        }
    ]
}
